aio_overpass/__init__.py
aio_overpass/_clock.py
aio_overpass/_dist.py
aio_overpass/_env.py
aio_overpass/client.py
aio_overpass/doc/coordinates.md
aio_overpass/doc/extras.md
aio_overpass/doc/usage.md
aio_overpass/element.py
aio_overpass/error.py
aio_overpass/pt.py
aio_overpass/pt_ordered.py
aio_overpass/py.typed
aio_overpass/ql.py
aio_overpass/query.py
aio_overpass/spatial.py
aio_overpass-0.15.1.dist-info/licenses/LICENSE
aio_overpass-0.15.1.dist-info/WHEEL
aio_overpass-0.15.1.dist-info/METADATA
aio_overpass-0.15.1.dist-info/RECORD
