Metadata-Version: 2.4
Name: aio-overpass
Version: 0.15.1
Summary: Async client for the Overpass API
Keywords: geojson,geospatial,gis,openstreetmap,osm,overpass-api,public-transport,spatial-analysis,spatial-data,shapely
Author: Tim Wiechers
Author-email: Tim Wiechers <mail@timwie.dev>
License-Expression: MIT
License-File: LICENSE
Classifier: Development Status :: 3 - Alpha
Classifier: Framework :: aiohttp
Classifier: Framework :: AsyncIO
Classifier: Intended Audience :: Developers
Classifier: Intended Audience :: Science/Research
Classifier: License :: OSI Approved :: MIT License
Classifier: Topic :: Scientific/Engineering :: GIS
Classifier: Topic :: Software Development :: Libraries :: Python Modules
Classifier: Topic :: Internet :: WWW/HTTP
Classifier: Typing :: Typed
Classifier: Operating System :: OS Independent
Classifier: Programming Language :: Python :: 3.11
Classifier: Programming Language :: Python :: 3.12
Classifier: Programming Language :: Python :: 3.13
Requires-Dist: aiohttp[speedups]>=3.9,<4
Requires-Dist: joblib>=1.3,<2 ; extra == 'joblib'
Requires-Dist: networkx>=3,<4 ; extra == 'networkx'
Requires-Dist: shapely>=2,<3 ; extra == 'shapely'
Requires-Python: >=3.11, <4
Project-URL: Release Notes, https://github.com/timwie/aio-overpass/blob/main/RELEASES.md
Project-URL: Test Coverage, https://codecov.io/gh/timwie/aio-overpass
Project-URL: documentation, https://www.timwie.dev/aio-overpass/
Project-URL: repository, https://github.com/timwie/aio-overpass
Provides-Extra: joblib
Provides-Extra: networkx
Provides-Extra: shapely
